{
  "balance": "balance",
  "bill": "bill",
  "payment methods": "payment methods",
  "month": "month",
  "billing history": "billing history",
  "payment": "payment",
  "automatic payments": "automatic payments",
  "late payment fees": "late payment fees",
  "account bill": "account bill",
  "account payment": "account payment",
  "credit card": "credit card",
  "payment method)(payment_method) for the [bill": "payment method)(payment_method) for the [bill",
  "july": "July",
  "international calls": "international calls",
  "network connection": "network connection",
  "area": "area",
  "network": "network",
  "network signal": "network signal",
  "network settings": "network settings",
  "network coverage": "network coverage",
  "call": "call",
  "service": "service",
  "4g": "4G",
  "5g": "5G",
  "roaming policy": "roaming policy",
  "signal strength": "signal strength",
  "networkk": "networkk",
  "plans": "plans",
  "plan": "plan",
  "family plan": "family plan",
  "group plan": "group plan",
  "prepaid": "prepaid",
  "postpaid": "postpaid",
  "family": "family",
  "individual": "individual"
}